tsloader/__init__.py
tsloader/datamodule.py
tsloader/dataset.py
tsloader/py.typed
tsloader-3.1.0.dist-info/LICENSE
tsloader-3.1.0.dist-info/METADATA
tsloader-3.1.0.dist-info/WHEEL
tsloader-3.1.0.dist-info/top_level.txt
tsloader-3.1.0.dist-info/RECORD
