Metadata-Version: 2.1
Name: tsloader
Version: 3.1.0
Summary: Load time series in pyTorch dataloaders.
Author-email: Max Cohen <max@zagouri.org>
License: MIT License
Project-URL: Homepage, https://git.zagouri.org/max/ts_loader
Classifier: Programming Language :: Python :: 3
Classifier: License :: OSI Approved :: MIT License
Classifier: Operating System :: OS Independent
Requires-Python: >=3.9.17
License-File: LICENSE
Requires-Dist: torch
Requires-Dist: lightning
Requires-Dist: pandas
Requires-Dist: pyarrow
